SerraWatchLogger/__init__.py
SerraWatchLogger/backend/LoggerSerraWatch.py
SerraWatchLogger/backend/__init__.py
SerraWatchLogger/config/__init__.py
SerraWatchLogger/config/config.yaml
serrawatchlogger-0.0.11.dist-info/METADATA
serrawatchlogger-0.0.11.dist-info/WHEEL
serrawatchlogger-0.0.11.dist-info/RECORD
